REPLAPI/__init__.py
REPLAPI/main.py
REPLAPI-0.0.6.dist-info/LICENSE
REPLAPI-0.0.6.dist-info/METADATA
REPLAPI-0.0.6.dist-info/WHEEL
REPLAPI-0.0.6.dist-info/top_level.txt
REPLAPI-0.0.6.dist-info/zip-safe
REPLAPI-0.0.6.dist-info/RECORD
