Metadata-Version: 2.1
Name: REPLAPI
Version: 0.0.6
Summary: REPLAPI Module
Home-page: https://github.com/JBYT27/REPLAPI
Author: darkdarcool30
Author-email: darkdarcool@gmail.com
License: MIT
Platform: UNKNOWN
Classifier: Programming Language :: Python :: 3
Classifier: License :: OSI Approved :: GNU General Public License v3 (GPLv3)
Classifier: Operating System :: OS Independent
Requires-Python: >=3.0
Requires-Dist: bs4
Requires-Dist: repltalk
